MANIFEST.in
README.md
setup.cfg
setup.py
twpy/__init__.py
twpy.egg-info/PKG-INFO
twpy.egg-info/SOURCES.txt
twpy.egg-info/dependency_links.txt
twpy.egg-info/requires.txt
twpy.egg-info/top_level.txt
twpy/config/__init__.py
twpy/config/config.py
twpy/core/__init__.py
twpy/core/grabber.py
twpy/core/request.py
twpy/exceptions/__init__.py
twpy/models/__init__.py
twpy/models/data_model.py
twpy/serializers/__init__.py
twpy/serializers/__to_json.py
twpy/serializers/__to_list.py
twpy/serializers/__to_pandas.py
twpy/utils/__init__.py