Metadata-Version: 2.1
Name: twpy
Version: 1.2.4
Summary: Twitter High level scraper for humans. 
Home-page: https://github.com/0x0ptim0us/twpy
Author: Fardin Allahverdinazhand
Author-email: 0x0ptim0us@gmail.com
License: MIT
Download-URL: https://github.com/0x0ptim0us/twpy/tarball/1.2.4
Keywords: python3,twitter,twitter api,twpy,twitter scraper
Platform: UNKNOWN
Classifier: Intended Audience :: Developers
Classifier: License :: OSI Approved :: MIT License
Classifier: Programming Language :: Python :: 3.5
Classifier: Programming Language :: Python :: 3.6
Classifier: Programming Language :: Python :: 3.7
Classifier: Programming Language :: Python :: 3.8
Classifier: Natural Language :: English
